base_sqlalchemy_repository/__init__.py
base_sqlalchemy_repository/base.py
base_sqlalchemy_repository/ops.py
base_sqlalchemy_repository/types.py
base_sqlalchemy_repository-0.1.0.dist-info/METADATA
base_sqlalchemy_repository-0.1.0.dist-info/WHEEL
base_sqlalchemy_repository-0.1.0.dist-info/licenses/LICENSE
base_sqlalchemy_repository-0.1.0.dist-info/RECORD
