Metadata-Version: 2.4
Name: base-sqlalchemy-repository
Version: 0.1.0
Summary: Async generic base repository for managing SQLAlchemy models.
License: MIT
License-File: LICENSE
Author: Saidkamol Mirsaidov
Author-email: kamolsaid2006@gmail.com
Requires-Python: >=3.12
Classifier: License :: OSI Approved :: MIT License
Classifier: Programming Language :: Python :: 3
Classifier: Programming Language :: Python :: 3.12
Classifier: Programming Language :: Python :: 3.13
Classifier: Programming Language :: Python :: 3.14
Requires-Dist: sqlalchemy (>=2.0.46,<3.0.0)
